pytest_integration/pytest_plugin.py
pytest_integration-0.2.3.dist-info/LICENSE
pytest_integration-0.2.3.dist-info/METADATA
pytest_integration-0.2.3.dist-info/WHEEL
pytest_integration-0.2.3.dist-info/entry_points.txt
pytest_integration-0.2.3.dist-info/top_level.txt
pytest_integration-0.2.3.dist-info/RECORD
