Metadata-Version: 2.1
Name: pytest-integration
Version: 0.2.3
Summary: Organizing pytests by integration or not
Home-page: https://github.com/jbwdevries/pytest-integration
Author: Johan B.W. de Vries
License: UNKNOWN
Project-URL: Bug Tracker, https://github.com/jbwdevries/pytest-integration/issues
Project-URL: Source Code, https://github.com/jbwdevries/pytest-integration
Platform: UNKNOWN
Classifier: License :: OSI Approved :: MIT License
Classifier: Programming Language :: Python :: 3
Classifier: Operating System :: OS Independent
Classifier: Framework :: Pytest
Requires-Python: >=3.6
